sdriving/__init__.py
sdriving/logging.py
sdriving/agents/__init__.py
sdriving/agents/buffer.py
sdriving/agents/model.py
sdriving/agents/utils.py
sdriving/agents/buffers/__init__.py
sdriving/agents/buffers/centralized_ppo_buffer.py
sdriving/agents/buffers/onestep_ppo_buffer.py
sdriving/agents/models/__init__.py
sdriving/agents/models/ppo_actor.py
sdriving/agents/models/ppo_actor_critic.py
sdriving/agents/models/ppo_critic.py
sdriving/agents/ppo_altopt/__init__.py
sdriving/agents/ppo_altopt/ppo.py
sdriving/agents/ppo_altopt/train.py
sdriving/agents/ppo_distributed/__init__.py
sdriving/agents/ppo_distributed/ppo.py
sdriving/agents/ppo_distributed/train.py
sdriving/agents/ppo_one_step/__init__.py
sdriving/agents/ppo_one_step/ppo.py
sdriving/agents/ppo_one_step/train.py
sdriving/environments/__init__.py
sdriving/environments/base_env.py
sdriving/environments/fixed_track.py
sdriving/environments/highway.py
sdriving/environments/intersection.py
sdriving/environments/nuscenes.py
sdriving/environments/spline_dual_objective_env.py
sdriving/environments/spline_env.py
sdriving/nuscenes/__init__.py
sdriving/nuscenes/nusc.py
sdriving/nuscenes/utils.py
sdriving/nuscenes/world.py
sdriving/scripts/__init__.py
sdriving/scripts/action_recorder.py
sdriving/scripts/ckpt_parser.py
sdriving/scripts/dump_locations.py
sdriving/scripts/record_parser.py
sdriving/scripts/rollout.py
sdriving/tsim/__init__.py
sdriving/tsim/common_networks.py
sdriving/tsim/dynamics.py
sdriving/tsim/objects.py
sdriving/tsim/parametric_curves.py
sdriving/tsim/road.py
sdriving/tsim/traffic_signal.py
sdriving/tsim/utils.py
sdriving/tsim/vehicle.py
sdriving/tsim/world.py
sdriving-0.1.0.dist-info/LICENSE
sdriving-0.1.0.dist-info/METADATA
sdriving-0.1.0.dist-info/WHEEL
sdriving-0.1.0.dist-info/top_level.txt
sdriving-0.1.0.dist-info/zip-safe
sdriving-0.1.0.dist-info/RECORD
