Metadata-Version: 2.1
Name: sdriving
Version: 0.1.0
Summary: Design multi-agent environments and simple reward functions such that social driving behavior emerges
Home-page: https://github.com/fidler-lab/social-driving/
Author: Avik Pal
Author-email: avikpal@cse.iitk.ac.in
License: MIT
Keywords: deep learning,pytorch,RL,AI
Platform: UNKNOWN
Classifier: Environment :: Console
Classifier: Natural Language :: English
Classifier: Development Status :: 5 - Production/Stable
Classifier: Intended Audience :: Developers
Classifier: Intended Audience :: Science/Research
Classifier: Topic :: Scientific/Engineering :: Artificial Intelligence
Classifier: License :: OSI Approved :: MIT License
Classifier: Operating System :: OS Independent
Classifier: Programming Language :: Python :: 3
Classifier: Programming Language :: Python :: 3.6
Classifier: Programming Language :: Python :: 3.7
Classifier: Programming Language :: Python :: 3.8
Classifier: License :: OSI Approved :: MIT License
Requires-Python: >=3.6
Requires-Dist: celluloid
Requires-Dist: gym
Requires-Dist: horovod
Requires-Dist: numpy
Requires-Dist: scipy
Requires-Dist: matplotlib
Requires-Dist: wandb (==0.9.5)
Requires-Dist: opencv-python
Requires-Dist: pyquaternion
Requires-Dist: fire
Requires-Dist: sklearn
